Workbook
Name Escenario: #REF!
Name TRM: #REF!
Name IPC: BPMS!$H$29
Name Escenario: BPMS!#REF!
Name IPC: BPMS!$H$29
Name TRM: BPMS!#REF!

Sheet Entradas Agendamiento
B1: Demanda / mes | E1: Personal | H1: Tiempos por solicitud AS-IS (min) | K1: Calidad | N1: Simulación BIMP
B2: 300 | C2: Solicitudes por día | E2: 4 | F2: Auxiliares de agendamiento | H2: 1.5 | I2: Recibir y leer la solicitud | K2: 0.1 | L2: Citas canceladas por error/autorización (hoy) | N2: 3.3 | O2: Tiempo promedio por solicitud AS-IS (horas)
B3: 22 | C3: Días hábiles al mes | E3: 8 | F3: Horas por día | H3: 2.5 | I3: Consultar paciente en portal EPS | K3: 0.03 | L3: Citas canceladas con la solución | N3: 7.3 | O3: Tiempo promedio por solicitud TO-BE (minutos)
B4: =B2*B3 | C4: Solicitudes al mes | E4: 1800000 | F4: Salario mensual por auxiliar | H4: 3 | I4: Buscar espacio y registrar cita | K4: 0.2 | L4: Inasistencia (hoy, sin recordatorio) | N4: 0.969 | O4: Ocupación de auxiliares AS-IS
B5: =B4*81% | C5: Citas asignadas al mes (81 % de las solicitudes, según simulación) | E5: 0.54 | F5: Factor prestacional | H5: 1 | I5: Confirmar al paciente | K5: 0.15 | L5: Inasistencia con recordatorio | N5: 0.273 | O5: Ocupación de auxiliares TO-BE
E6: =E4*(1+E5)/(E3*B3) | F6: Costo por hora de un auxiliar | H6: =SUM(H2:H5) | I6: Total por solicitud | K6: 35000 | L6: Valor promedio de una consulta
K7: 0.7 | L7: Margen de contribución de la consulta

Sheet BPMS
D1: CASO DE NEGOCIO: AUTOMATIZACIÓN DE ASIGNACIÓN DE CITAS MÉDICAS
A5: Liberación de Tiempo | G5: Desarrollo del caso de negocio
A6: Tarea Impactada | B6: Proceso | C6: Costo de la Tarea | D6: Cant. de repeticiones mes | E6: Tiempo de la Tarea (Horas) | G6: Periodo (Mes) | H6: Liberación de Tiempo | I6: Otros Beneficios | J6: Egresos (Costos del caso de negocio) | K6: Flujo de Caja | L6: Flujo de Caja acumulado
A7: Recibir y leer la solicitud (teléfono, WhatsApp, correo) | B7: Asignación de citas médicas | C7: =D7*E7*'Entradas Agendamiento'!$E$6 | D7: ='Entradas Agendamiento'!$B$4 | E7: ='Entradas Agendamiento'!H2/60 | G7: 0 | H7: 0 | I7: 0 | J7: =($B$22+$B$23)/2 | K7: =(I7+H7)-J7 | L7: =K7
A8: Consultar paciente y autorización en portal EPS | B8: Asignación de citas médicas | C8: =D8*E8*'Entradas Agendamiento'!$E$6 | D8: ='Entradas Agendamiento'!$B$4 | E8: ='Entradas Agendamiento'!H3/60 | G8: 1 | H8: =$C$13 | I8: 0 | J8: =($B$22+$B$23)/2 | K8: =(I8+H8)-J8 | L8: =L7+K8
A9: Buscar espacio y registrar la cita | B9: Asignación de citas médicas | C9: =D9*E9*'Entradas Agendamiento'!$E$6 | D9: ='Entradas Agendamiento'!$B$4 | E9: ='Entradas Agendamiento'!H4/60 | G9: 2 | H9: =$C$13 | I9: 0 | J9: =($B$24+$B$25)/12 | K9: =(I9+H9)-J9 | L9: =L8+K9
A10: Confirmar la cita al paciente | B10: Asignación de citas médicas | C10: =D10*E10*'Entradas Agendamiento'!$E$6 | D10: ='Entradas Agendamiento'!$B$4 | E10: ='Entradas Agendamiento'!H5/60 | G10: 3 | H10: =$C$13 | I10: 0 | J10: =($B$24+$B$25)/12 | K10: =(H10+I10)-J10 | L10: =L9+K10
G11: 4 | H11: =$C$13 | I11: 0 | J11: =($B$24+$B$25)/12 | K11: =(I11+H11)-J11 | L11: =L10+K11
G12: 5 | H12: =$C$13 | I12: 0 | J12: =($B$24+$B$25)/12 | K12: =(I12+H12)-J12 | L12: =L11+K12
A13: Disminución costo del Recurso para el Proceso | C13: =(4-2)*'Entradas Agendamiento'!$E$4*(1+'Entradas Agendamiento'!$E$5) | D13: Pasar de 4 a 2 auxiliares (salario + prestaciones), por mes | G13: 6 | H13: =$C$13 | I13: =SUM($B$17:$B$18) | J13: =($B$24+$B$25)/12 | K13: =(I13+H13)-J13 | L13: =L12+K13
G14: 7 | H14: =$C$13 | I14: =SUM($B$17:$B$18) | J14: =($B$24+$B$25)/12 | K14: =(I14+H14)-J14 | L14: =L13+K14
A15: Otros Beneficios | G15: 8 | H15: =$C$13 | I15: =SUM($B$17:$B$18) | J15: =($B$24+$B$25)/12 | K15: =(I15+H15)-J15 | L15: =L14+K15
A16: Descripción | B16: Costo | C16: Observación | G16: 9 | H16: =$C$13 | I16: =SUM($B$17:$B$18) | J16: =($B$24+$B$25)/12 | K16: =(I16+H16)-J16 | L16: =L15+K16
A17: Menos citas canceladas por error o falta de autorización (10 % → 3 %) | B17: ='Entradas Agendamiento'!B5*('Entradas Agendamiento'!K2-'Entradas Agendamiento'!K3)*50%*'Entradas Agendamiento'!K6*'Entradas Agendamiento'!K7 | C17: Se reocupa la mitad de los espacios recuperados; valor = margen de la consulta | G17: 10 | H17: =$C$13 | I17: =SUM($B$17:$B$18) | J17: =($B$24+$B$25)/12 | K17: =(I17+H17)-J17 | L17: =L16+K17
A18: Menos inasistencia gracias al recordatorio (20 % → 15 %) | B18: ='Entradas Agendamiento'!B5*('Entradas Agendamiento'!K4-'Entradas Agendamiento'!K5)*'Entradas Agendamiento'!K6*'Entradas Agendamiento'!K7 | C18: Citas que sí se atienden; valor = margen de la consulta | G18: 11 | H18: =$C$13 | I18: =SUM($B$17:$B$18) | J18: =($B$24+$B$25)/12 | K18: =(I18+H18)-J18 | L18: =L17+K18
G19: 12 | H19: =$C$13 | I19: =SUM($B$17:$B$18) | J19: =($B$24+$B$25)/12 | K19: =(I19+H19)-J19 | L19: =L18+K19
A20: Egresos (Costos del caso de negocio)
A21: Descripción | B21: Costo | C21: Observación | G21: Periodo (Mes) | H21: Liberación de Tiempo | I21: Otros Beneficios | J21: Egresos (Costos del caso de negocio) | K21: Flujo de Caja | L21: Flujo de Caja acumulado
A22: Desarrollo de la solución (bots RPA, flujos n8n e IA) | B22: 45000000 | C22: Pago única vez | G22: Inversión Inicial | H22: 0 | I22: 0 | J22: =J7 | K22: =K7 | L22: =K22
A23: Implementación (Ley 1581, capacitación, salida de 2 auxiliares) | B23: 13000000 | C23: Pago única vez | G23: Total Año 1 | H23: =SUM(H8:H19) | I23: =SUM(I8:I19) | J23: =SUM(J8:J19) | K23: =(I23+H23)-J23 | L23: =L22+K23
A24: Licenciamiento (API de IA, WhatsApp, telefonía) | B24: 14400000 | C24: Pago anual | G24: Total Año 2 | H24: =H23*(1+IPC) | I24: =SUM($B$17:$B$18)*12*(1+IPC) | J24: =($B$24+$B$25)*(1+IPC) | K24: =(I24+H24)-J24 | L24: =L23+K24
A25: Soporte, Mantenimiento e Infraestructura (servidor n8n en la nube) | B25: 27600000 | C25: Pago anual | G25: Total Año 3 | H25: =H24*(1+IPC) | I25: =I24*(1+IPC) | J25: =J24*(1+IPC) | K25: =(I25+H25)-J25 | L25: =L24+K25
G26: TOTAL | H26: =SUM(H23:H25) | I26: =SUM(I23:I25) | J26: =SUM(J22:J25) | K26: =SUM(K22:K25)
G28: Parametros | J28: Indicadores Fianancieros
G29: Inflación | H29: 0.05 | J29: Tiempo de Recuperación | L29: =IF(COUNTIF(L7:L19,"<0")>12,"Después del mes 12","Mes "&COUNTIF(L7:L19,"<0"))
G30: Periodos | H30: Anuales | J30: Valor Presente Neto (VPN) | L30: =NPV(IPC,K23:K25)+K22
G31: Tiempo | H31: 3 años | J31: Tasa Interna de Retorno | L31: =IRR(K22:K25)
J32: Recursos de Apalancamiento | L32: =-MIN(L7:L19)
J33: Retorno de Inversión | L33: =((I26+H26)-L32)/L32
J34: Retorno de Inversión | L34: =SUM(I26+H26)-L32
